{
    "type": "object",
    "properties": {
        "endTime": {
            "type": "string"
        },
        "includeDeleted": {
            "type": "boolean"
        },
        "pageToken": {
            "type": "string"
        },
        "startTime": {
            "type": "string"
        },
        "userId": {
            "required": true,
            "type": "string"
        },
        "quotaUser": {
            "type": "string"
        },
        "userIp": {
            "type": "string"
        }
    }
}